adafruit_pixelmap.py
adafruit_circuitpython_pixelmap-1.0.10.dist-info/licenses/LICENSE
adafruit_circuitpython_pixelmap-1.0.10.dist-info/METADATA
adafruit_circuitpython_pixelmap-1.0.10.dist-info/WHEEL
adafruit_circuitpython_pixelmap-1.0.10.dist-info/top_level.txt
adafruit_circuitpython_pixelmap-1.0.10.dist-info/RECORD
