Metadata-Version: 2.4
Name: adafruit-circuitpython-pixelmap
Version: 1.0.10
Summary: CircuitPython library for mapping multiple neopixels to behave as one for the purposes of setting colors or showing animations.
Author-email: Adafruit Industries <circuitpython@adafruit.com>
License: MIT
Project-URL: Homepage, https://github.com/adafruit/Adafruit_CircuitPython_PixelMap
Keywords: adafruit,blinka,circuitpython,micropython,pixelmap,led,neopixel,lights,rgb,animation,led_animation
Classifier: Intended Audience :: Developers
Classifier: Topic :: Software Development :: Libraries
Classifier: Topic :: Software Development :: Embedded Systems
Classifier: Topic :: System :: Hardware
Classifier: License :: OSI Approved :: MIT License
Classifier: Programming Language :: Python :: 3
License-File: LICENSE
Requires-Dist: Adafruit-Blinka
Provides-Extra: optional
Dynamic: license-file
